hello_lib1234/__init__.py
hello_lib1234/core.py
hello_lib1234-0.1.0.dist-info/licenses/LICENSE
hello_lib1234-0.1.0.dist-info/METADATA
hello_lib1234-0.1.0.dist-info/WHEEL
hello_lib1234-0.1.0.dist-info/top_level.txt
hello_lib1234-0.1.0.dist-info/RECORD
