Metadata-Version: 2.4
Name: hello-lib1234
Version: 0.1.0
Summary: A simple Python library that says hello
Author-email: Alice Example <alice@example.com>
License: MIT
Project-URL: Homepage, https://github.com/yourusername/hello-lib
Requires-Python: >=3.8
License-File: LICENSE
Dynamic: license-file
